django_trips/__init__.py
django_trips/admin.py
django_trips/apps.py
django_trips/choices.py
django_trips/managers.py
django_trips/mixins.py
django_trips/models.py
django_trips/permissions.py
django_trips/tests.py
django_trips/urls.py
django_trips/utils.py
django_trips/views.py
django_trips-1.0.4.dist-info/licenses/AUTHORS
django_trips-1.0.4.dist-info/licenses/LICENSE
django_trips-1.0.4.dist-info/METADATA
django_trips-1.0.4.dist-info/WHEEL
django_trips-1.0.4.dist-info/entry_points.txt
django_trips-1.0.4.dist-info/top_level.txt
django_trips-1.0.4.dist-info/RECORD
