Metadata-Version: 2.4
Name: django-trips
Version: 1.0.4
Summary: A Django Rest API for fetching and creating trips and their schedules.
Home-page: https://github.com/awaisdar001/django-trips
Author: Awais Jibran
Author-email: awaisdar001@gmail.com
License: MIT
Keywords: Django trips
Classifier: Intended Audience :: Developers
Classifier: License :: OSI Approved :: MIT License
Classifier: Operating System :: OS Independent
Classifier: Programming Language :: Python :: 3.11
Classifier: Programming Language :: Python :: 3.12
Requires-Python: >=3.11
License-File: LICENSE
License-File: AUTHORS
Requires-Dist: pytz==2025.2
Requires-Dist: docutils==0.21.2
Requires-Dist: isort==5.13.2
Requires-Dist: sqlparse==0.5.3
Requires-Dist: pytest==7.4.3
Requires-Dist: edx-django-utils==4.2.0
Requires-Dist: ddt==1.4.2
Requires-Dist: django-extensions==3.2.3
Requires-Dist: djangorestframework_simplejwt==5.5.0
Requires-Dist: psutil==5.9.5
Requires-Dist: twine==6.1.0
Requires-Dist: mysqlclient==2.2.1
Requires-Dist: PyJWT==2.9.0
Requires-Dist: factory-boy==3.3.0
Requires-Dist: pylint-plugin-utils==0.8.2
Requires-Dist: django-crum==0.7.9
Requires-Dist: pylint-django==2.6.1
Requires-Dist: django-cors-headers==4.0.0
Requires-Dist: python-dateutil==2.8.2
Requires-Dist: Django<4.3
Requires-Dist: drf-spectacular==0.28.0
Requires-Dist: djangorestframework==3.15.2
Requires-Dist: Faker==13.15.0
Requires-Dist: pylint==3.3.7
Requires-Dist: setuptools==80.9.0
Requires-Dist: markdown==3.5.2
Requires-Dist: django-waffle==4.2.0
Requires-Dist: PyYAML==6.0.2
Requires-Dist: django-countries==7.6.1
Requires-Dist: django-filter==23.2
Requires-Dist: django-taggit==6.1.0
Requires-Dist: django-config-models==2.7.0
Requires-Dist: pytest-django==4.5.2
Requires-Dist: path==16.3.0
Requires-Dist: requests==2.32.4
Provides-Extra: dev
Requires-Dist: wheel; extra == "dev"
Requires-Dist: twine; extra == "dev"
Requires-Dist: pytest; extra == "dev"
Dynamic: author
Dynamic: author-email
Dynamic: classifier
Dynamic: description
Dynamic: description-content-type
Dynamic: home-page
Dynamic: keywords
Dynamic: license
Dynamic: license-file
Dynamic: provides-extra
Dynamic: requires-dist
Dynamic: requires-python
Dynamic: summary
